odoo/addons/attachment_category/README.rst
odoo/addons/attachment_category/__init__.py
odoo/addons/attachment_category/__manifest__.py
odoo/addons/attachment_category/i18n/attachment_category.pot
odoo/addons/attachment_category/i18n/es.po
odoo/addons/attachment_category/i18n/it.po
odoo/addons/attachment_category/models/__init__.py
odoo/addons/attachment_category/models/ir_attachment.py
odoo/addons/attachment_category/models/ir_attachment_category.py
odoo/addons/attachment_category/readme/CONTRIBUTORS.md
odoo/addons/attachment_category/readme/DESCRIPTION.md
odoo/addons/attachment_category/readme/USAGE.md
odoo/addons/attachment_category/security/ir_attachment_category.xml
odoo/addons/attachment_category/static/description/icon.png
odoo/addons/attachment_category/static/description/index.html
odoo/addons/attachment_category/views/ir_attachment.xml
odoo/addons/attachment_category/views/ir_attachment_category.xml
odoo_addon_attachment_category-17.0.1.0.1.3.dist-info/METADATA
odoo_addon_attachment_category-17.0.1.0.1.3.dist-info/WHEEL
odoo_addon_attachment_category-17.0.1.0.1.3.dist-info/top_level.txt
odoo_addon_attachment_category-17.0.1.0.1.3.dist-info/RECORD
